SlideRunner/SlideRunner.py
SlideRunner/Slides.sqlite
SlideRunner/__init__.py
SlideRunner/__main__.py
SlideRunner/artwork/AboutScreen.png
SlideRunner/artwork/ExactWelcomeScreen.png
SlideRunner/artwork/SlideRunnerDMG.png
SlideRunner/artwork/SplashScreen.png
SlideRunner/artwork/annoInOverview.png
SlideRunner/artwork/backArrow.png
SlideRunner/artwork/blindedMode.png
SlideRunner/artwork/drawCircle.png
SlideRunner/artwork/icon.png
SlideRunner/artwork/iconArrow.png
SlideRunner/artwork/iconBlinded.png
SlideRunner/artwork/iconCircle.png
SlideRunner/artwork/iconOverlay.png
SlideRunner/artwork/iconPolygon.png
SlideRunner/artwork/iconQuestion.png
SlideRunner/artwork/iconRect.png
SlideRunner/artwork/iconWand.png
SlideRunner/artwork/icon_flag.png
SlideRunner/artwork/icon_nextView.png
SlideRunner/artwork/icon_previousView.png
SlideRunner/artwork/icon_screeningMode.png
SlideRunner/dataAccess/__init__.py
SlideRunner/dataAccess/annotations.py
SlideRunner/dataAccess/cellvizio.py
SlideRunner/dataAccess/database.py
SlideRunner/dataAccess/dicom.py
SlideRunner/dataAccess/exact.py
SlideRunner/dataAccess/nifty.py
SlideRunner/dataAccess/slide.py
SlideRunner/general/SlideRunnerPlugin.py
SlideRunner/general/__init__.py
SlideRunner/general/dependencies.py
SlideRunner/general/pluginFinder.py
SlideRunner/general/types.py
SlideRunner/gui/SlideRunner_ui.py
SlideRunner/gui/__init__.py
SlideRunner/gui/annotation.py
SlideRunner/gui/frameSlider.py
SlideRunner/gui/menu.py
SlideRunner/gui/mouseEvents.py
SlideRunner/gui/shortcuts.py
SlideRunner/gui/sidebar.py
SlideRunner/gui/splashScreen.py
SlideRunner/gui/style.py
SlideRunner/gui/toolbar.py
SlideRunner/gui/types.py
SlideRunner/gui/zoomSlider.py
SlideRunner/gui/dialogs/__init__.py
SlideRunner/gui/dialogs/about.py
SlideRunner/gui/dialogs/dbmanager.py
SlideRunner/gui/dialogs/exactDownloadDialog.py
SlideRunner/gui/dialogs/exactLinkDialog.py
SlideRunner/gui/dialogs/getCoordinates.py
SlideRunner/gui/dialogs/question.py
SlideRunner/gui/dialogs/settings.py
SlideRunner-2.0.dist-info/LICENSE
SlideRunner-2.0.dist-info/METADATA
SlideRunner-2.0.dist-info/WHEEL
SlideRunner-2.0.dist-info/entry_points.txt
SlideRunner-2.0.dist-info/top_level.txt
SlideRunner-2.0.dist-info/RECORD
