Metadata-Version: 2.1
Name: SlideRunner
Version: 2.0
Summary: SlideRunner - A Tool for Massive Cell Annotations in Whole Slide Images
Home-page: http://github.com/maubreville/SlideRunner
Author: Marc Aubreville
Author-email: marc.aubreville@fau.de
License: GPL
Platform: UNKNOWN
Requires-Dist: PyQt5
Requires-Dist: openslide-python (>=1.1.1)
Requires-Dist: pyqt5 (>=5.5.0)
Requires-Dist: opencv-python (>=3.1.0)
Requires-Dist: matplotlib (>=2.0.0)
Requires-Dist: numpy (>=1.13)
Requires-Dist: rollbar (>=0.14)
Requires-Dist: shapely (>=1.6.4)
Requires-Dist: pydicom (>=1.4.1)
